Metadata-Version: 2.1
Name: PyTic
Version: 0.0.4
Summary: An object-oriented Python wrapper for Pololu Tic Stepper Controllers.
Home-page: https://github.com/AllenInstitute/pytic
Author: Daniel Castelli
Author-email: danc@alleninstitute.org
License: Allen Institute Software License
Keywords: PyTic Pololu Tic Stepper Controller Wrapper
Platform: UNKNOWN
